__init__.py
shared.py
commands/exec.py
events/loop.py
events/processLoop.py
nonebot_plugin_system_tools-0.0.1.dist-info/LICENSE
nonebot_plugin_system_tools-0.0.1.dist-info/METADATA
nonebot_plugin_system_tools-0.0.1.dist-info/WHEEL
nonebot_plugin_system_tools-0.0.1.dist-info/top_level.txt
nonebot_plugin_system_tools-0.0.1.dist-info/RECORD
