Metadata-Version: 2.1
Name: nonebot-plugin-system-tools
Version: 0.0.1
Summary: system-tools (rebuild from npm:koishi-plugin-systools)
Requires-Python: <4.0,>=3.9
License-File: LICENSE
